{
  "id": "abab32a2-c11f-41ad-a6fc-2fa33d3ecb58",
  "realm": "techmarket-realm",
  "notBefore": 0,
  "defaultSignatureAlgorithm": "RS256",
  "revokeRefreshToken": false,
  "refreshTokenMaxReuse": 0,
  "accessTokenLifespan": 300,
  "accessTokenLifespanForImplicitFlow": 900,
  "ssoSessionIdleTimeout": 1800,
  "ssoSessionMaxLifespan": 36000,
  "ssoSessionIdleTimeoutRememberMe": 0,
  "ssoSessionMaxLifespanRememberMe": 0,
  "offlineSessionIdleTimeout": 2592000,
  "offlineSessionMaxLifespanEnabled": false,
  "offlineSessionMaxLifespan": 5184000,
  "clientSessionIdleTimeout": 0,
  "clientSessionMaxLifespan": 0,
  "clientOfflineSessionIdleTimeout": 0,
  "clientOfflineSessionMaxLifespan": 0,
  "accessCodeLifespan": 60,
  "accessCodeLifespanUserAction": 300,
  "accessCodeLifespanLogin": 1800,
  "actionTokenGeneratedByAdminLifespan": 43200,
  "actionTokenGeneratedByUserLifespan": 300,
  "oauth2DeviceCodeLifespan": 600,
  "oauth2DevicePollingInterval": 5,
  "enabled": true,
  "sslRequired": "external",
  "registrationAllowed": false,
  "registrationEmailAsUsername": false,
  "rememberMe": false,
  "verifyEmail": false,
  "loginWithEmailAllowed": true,
  "duplicateEmailsAllowed": false,
  "resetPasswordAllowed": false,
  "editUsernameAllowed": false,
  "bruteForceProtected": false,
  "permanentLockout": false,
  "maxTemporaryLockouts": 0,
  "bruteForceStrategy": "MULTIPLE",
  "maxFailureWaitSeconds": 900,
  "minimumQuickLoginWaitSeconds": 60,
  "waitIncrementSeconds": 60,
  "quickLoginCheckMilliSeconds": 1000,
  "maxDeltaTimeSeconds": 43200,
  "failureFactor": 30,
  "maxSecondaryAuthFailures": 0,
  "roles": {
    "realm": [
      {
        "id": "4b74b19b-3253-457b-bec6-153d0d917d78",
        "name": "default-roles-techmarket-realm",
        "description": "${role_default-roles}",
        "composite": true,
        "composites": {
          "realm": [
            "offline_access",
            "uma_authorization"
          ],
          "client": {
            "account": [
              "view-profile",
              "manage-account"
            ]
          }
        },
        "clientRole": false,
        "containerId": "abab32a2-c11f-41ad-a6fc-2fa33d3ecb58",
        "attributes": {}
      },
      {
        "id": "bb2cc398-6749-4a29-85bd-37888029008e",
        "name": "offline_access",
        "description": "${role_offline-access}",
        "composite": false,
        "clientRole": false,
        "containerId": "abab32a2-c11f-41ad-a6fc-2fa33d3ecb58",
        "attributes": {}
      },
      {
        "id": "d8c009e0-f2da-4396-9f13-bf6e45bdbcc6",
        "name": "uma_authorization",
        "description": "${role_uma_authorization}",
        "composite": false,
        "clientRole": false,
        "containerId": "abab32a2-c11f-41ad-a6fc-2fa33d3ecb58",
        "attributes": {}
      }
    ],
    "client": {
      "realm-management": [
        {
          "id": "9cf4c241-e415-49b8-a246-d72f22ea51fd",
          "name": "manage-authorization",
          "description": "${role_manage-authorization}",
          "composite": false,
          "clientRole": true,
          "containerId": "f4f19fd1-87ce-40b0-afca-aefb080d2092",
          "attributes": {}
        },
        {
          "id": "80d4be8c-942c-4430-be10-f32b5392a4de",
          "name": "view-events",
          "description": "${role_view-events}",
          "composite": false,
          "clientRole": true,
          "containerId": "f4f19fd1-87ce-40b0-afca-aefb080d2092",
          "attributes": {}
        },
        {
          "id": "e94ef0fb-672b-41d5-a549-afba4616f8b5",
          "name": "view-realm",
          "description": "${role_view-realm}",
          "composite": false,
          "clientRole": true,
          "containerId": "f4f19fd1-87ce-40b0-afca-aefb080d2092",
          "attributes": {}
        },
        {
          "id": "0eadbd5b-88f4-4f08-bd37-84d69ed1fdea",
          "name": "view-identity-providers",
          "description": "${role_view-identity-providers}",
          "composite": false,
          "clientRole": true,
          "containerId": "f4f19fd1-87ce-40b0-afca-aefb080d2092",
          "attributes": {}
        },
        {
          "id": "78286d5a-e9aa-423b-a69d-efd4c0736126",
          "name": "manage-users",
          "description": "${role_manage-users}",
          "composite": false,
          "clientRole": true,
          "containerId": "f4f19fd1-87ce-40b0-afca-aefb080d2092",
          "attributes": {}
        },
        {
          "id": "6ebb1897-1723-4459-9314-790e2bcfc2ce",
          "name": "manage-identity-providers",
          "description": "${role_manage-identity-providers}",
          "composite": false,
          "clientRole": true,
          "containerId": "f4f19fd1-87ce-40b0-afca-aefb080d2092",
          "attributes": {}
        },
        {
          "id": "07ffdbdb-ae73-45f7-bf6d-22c0f83a3f86",
          "name": "query-users",
          "description": "${role_query-users}",
          "composite": false,
          "clientRole": true,
          "containerId": "f4f19fd1-87ce-40b0-afca-aefb080d2092",
          "attributes": {}
        },
        {
          "id": "e1fda715-694f-4e66-8f50-06cbb2bacb07",
          "name": "realm-admin",
          "description": "${role_realm-admin}",
          "composite": true,
          "composites": {
            "client": {
              "realm-management": [
                "manage-authorization",
                "view-events",
                "view-realm",
                "view-identity-providers",
                "manage-users",
                "manage-identity-providers",
                "query-users",
                "create-client",
                "view-users",
                "manage-realm",
                "manage-clients",
                "impersonation",
                "view-clients",
                "query-groups",
                "query-clients",
                "query-realms",
                "manage-events",
                "view-authorization"
              ]
            }
          },
          "clientRole": true,
          "containerId": "f4f19fd1-87ce-40b0-afca-aefb080d2092",
          "attributes": {}
        },
        {
          "id": "af81759e-36a4-45af-a35d-a17e0959972c",
          "name": "create-client",
          "description": "${role_create-client}",
          "composite": false,
          "clientRole": true,
          "containerId": "f4f19fd1-87ce-40b0-afca-aefb080d2092",
          "attributes": {}
        },
        {
          "id": "fe002134-8322-44e8-8ad5-746efe60918c",
          "name": "view-users",
          "description": "${role_view-users}",
          "composite": true,
          "composites": {
            "client": {
              "realm-management": [
                "query-groups",
                "query-users"
              ]
            }
          },
          "clientRole": true,
          "containerId": "f4f19fd1-87ce-40b0-afca-aefb080d2092",
          "attributes": {}
        },
        {
          "id": "85aba7f8-99f5-4c7a-8cd4-be6dc8a971d1",
          "name": "manage-realm",
          "description": "${role_manage-realm}",
          "composite": false,
          "clientRole": true,
          "containerId": "f4f19fd1-87ce-40b0-afca-aefb080d2092",
          "attributes": {}
        },
        {
          "id": "3aff1e43-fca6-416d-bd8b-82e9d3bac8a0",
          "name": "manage-clients",
          "description": "${role_manage-clients}",
          "composite": false,
          "clientRole": true,
          "containerId": "f4f19fd1-87ce-40b0-afca-aefb080d2092",
          "attributes": {}
        },
        {
          "id": "36f45212-670b-41ac-95c7-21b6650b8fb0",
          "name": "impersonation",
          "description": "${role_impersonation}",
          "composite": false,
          "clientRole": true,
          "containerId": "f4f19fd1-87ce-40b0-afca-aefb080d2092",
          "attributes": {}
        },
        {
          "id": "b6312fd4-1066-4f2c-9502-339929a7e8d6",
          "name": "view-clients",
          "description": "${role_view-clients}",
          "composite": true,
          "composites": {
            "client": {
              "realm-management": [
                "query-clients"
              ]
            }
          },
          "clientRole": true,
          "containerId": "f4f19fd1-87ce-40b0-afca-aefb080d2092",
          "attributes": {}
        },
        {
          "id": "ac0c041b-885f-4720-ade4-241b6ad87ae1",
          "name": "query-clients",
          "description": "${role_query-clients}",
          "composite": false,
          "clientRole": true,
          "containerId": "f4f19fd1-87ce-40b0-afca-aefb080d2092",
          "attributes": {}
        },
        {
          "id": "40316ea5-0e44-44b5-9cf2-97cedaac8cda",
          "name": "query-groups",
          "description": "${role_query-groups}",
          "composite": false,
          "clientRole": true,
          "containerId": "f4f19fd1-87ce-40b0-afca-aefb080d2092",
          "attributes": {}
        },
        {
          "id": "fde22e55-370e-4874-bd22-6ddc994b2388",
          "name": "query-realms",
          "description": "${role_query-realms}",
          "composite": false,
          "clientRole": true,
          "containerId": "f4f19fd1-87ce-40b0-afca-aefb080d2092",
          "attributes": {}
        },
        {
          "id": "60535a82-5ecf-46b9-9b7a-c7ebd19fe07b",
          "name": "manage-events",
          "description": "${role_manage-events}",
          "composite": false,
          "clientRole": true,
          "containerId": "f4f19fd1-87ce-40b0-afca-aefb080d2092",
          "attributes": {}
        },
        {
          "id": "aca10c63-aeb4-43a5-8488-0cc7a78329c6",
          "name": "view-authorization",
          "description": "${role_view-authorization}",
          "composite": false,
          "clientRole": true,
          "containerId": "f4f19fd1-87ce-40b0-afca-aefb080d2092",
          "attributes": {}
        }
      ],
      "security-admin-console": [],
      "admin-cli": [],
      "techmarket-client": [],
      "account-console": [],
      "broker": [
        {
          "id": "3b02682d-88af-4339-ac31-807a1da5a77b",
          "name": "read-token",
          "description": "${role_read-token}",
          "composite": false,
          "clientRole": true,
          "containerId": "557b4cac-ca7f-4fff-a895-1545ee59b69a",
          "attributes": {}
        }
      ],
      "account": [
        {
          "id": "377ded75-587c-42e3-98c1-bba0e44e43ac",
          "name": "view-groups",
          "description": "${role_view-groups}",
          "composite": false,
          "clientRole": true,
          "containerId": "1a69a001-5593-4d16-8160-c71531dc78a0",
          "attributes": {}
        },
        {
          "id": "2c0ed787-493c-4f90-9f32-135656effb60",
          "name": "delete-account",
          "description": "${role_delete-account}",
          "composite": false,
          "clientRole": true,
          "containerId": "1a69a001-5593-4d16-8160-c71531dc78a0",
          "attributes": {}
        },
        {
          "id": "f8b0edbc-9271-4648-a1a7-f6d9c422ed93",
          "name": "view-applications",
          "description": "${role_view-applications}",
          "composite": false,
          "clientRole": true,
          "containerId": "1a69a001-5593-4d16-8160-c71531dc78a0",
          "attributes": {}
        },
        {
          "id": "174da4d6-c200-4353-aefe-052e3e34a880",
          "name": "manage-account-links",
          "description": "${role_manage-account-links}",
          "composite": false,
          "clientRole": true,
          "containerId": "1a69a001-5593-4d16-8160-c71531dc78a0",
          "attributes": {}
        },
        {
          "id": "360ab3cb-cffd-4b34-870d-d4ca5e6726a8",
          "name": "view-profile",
          "description": "${role_view-profile}",
          "composite": false,
          "clientRole": true,
          "containerId": "1a69a001-5593-4d16-8160-c71531dc78a0",
          "attributes": {}
        },
        {
          "id": "86b92fc6-6ec9-4f05-bd55-b6140718b0f6",
          "name": "view-consent",
          "description": "${role_view-consent}",
          "composite": false,
          "clientRole": true,
          "containerId": "1a69a001-5593-4d16-8160-c71531dc78a0",
          "attributes": {}
        },
        {
          "id": "7bee7e20-3068-4aa1-94e4-df5555e81122",
          "name": "manage-consent",
          "description": "${role_manage-consent}",
          "composite": true,
          "composites": {
            "client": {
              "account": [
                "view-consent"
              ]
            }
          },
          "clientRole": true,
          "containerId": "1a69a001-5593-4d16-8160-c71531dc78a0",
          "attributes": {}
        },
        {
          "id": "48946e7f-dd29-4cbc-ad48-6dd5a3a19201",
          "name": "manage-account",
          "description": "${role_manage-account}",
          "composite": true,
          "composites": {
            "client": {
              "account": [
                "manage-account-links"
              ]
            }
          },
          "clientRole": true,
          "containerId": "1a69a001-5593-4d16-8160-c71531dc78a0",
          "attributes": {}
        }
      ]
    }
  },
  "groups": [],
  "defaultRole": {
    "id": "4b74b19b-3253-457b-bec6-153d0d917d78",
    "name": "default-roles-techmarket-realm",
    "description": "${role_default-roles}",
    "composite": true,
    "clientRole": false,
    "containerId": "abab32a2-c11f-41ad-a6fc-2fa33d3ecb58"
  },
  "requiredCredentials": [
    "password"
  ],
  "otpPolicyType": "totp",
  "otpPolicyAlgorithm": "HmacSHA1",
  "otpPolicyInitialCounter": 0,
  "otpPolicyDigits": 6,
  "otpPolicyLookAheadWindow": 1,
  "otpPolicyPeriod": 30,
  "otpPolicyCodeReusable": false,
  "otpSupportedApplications": [
    "totpAppFreeOTPName",
    "totpAppGoogleName",
    "totpAppMicrosoftAuthenticatorName"
  ],
  "localizationTexts": {},
  "webAuthnPolicyRpEntityName": "keycloak",
  "webAuthnPolicySignatureAlgorithms": [
    "ES256",
    "RS256"
  ],
  "webAuthnPolicyRpId": "",
  "webAuthnPolicyAttestationConveyancePreference": "not specified",
  "webAuthnPolicyAuthenticatorAttachment": "not specified",
  "webAuthnPolicyRequireResidentKey": "not specified",
  "webAuthnPolicyUserVerificationRequirement": "not specified",
  "webAuthnPolicyCreateTimeout": 0,
  "webAuthnPolicyAvoidSameAuthenticatorRegister": false,
  "webAuthnPolicyAcceptableAaguids": [],
  "webAuthnPolicyExtraOrigins": [],
  "webAuthnPolicyPasswordlessRpEntityName": "keycloak",
  "webAuthnPolicyPasswordlessSignatureAlgorithms": [
    "ES256",
    "RS256"
  ],
  "webAuthnPolicyPasswordlessRpId": "",
  "webAuthnPolicyPasswordlessAttestationConveyancePreference": "not specified",
  "webAuthnPolicyPasswordlessAuthenticatorAttachment": "not specified",
  "webAuthnPolicyPasswordlessRequireResidentKey": "Yes",
  "webAuthnPolicyPasswordlessUserVerificationRequirement": "required",
  "webAuthnPolicyPasswordlessCreateTimeout": 0,
  "webAuthnPolicyPasswordlessAvoidSameAuthenticatorRegister": false,
  "webAuthnPolicyPasswordlessAcceptableAaguids": [],
  "webAuthnPolicyPasswordlessExtraOrigins": [],
  "users": [
    {
      "id": "fc290796-0aad-4c07-9979-65dae2308edc",
      "username": "service-account-techmarket-client",
      "emailVerified": false,
      "enabled": true,
      "createdTimestamp": 1776005005506,
      "totp": false,
      "serviceAccountClientId": "techmarket-client",
      "disableableCredentialTypes": [],
      "requiredActions": [],
      "realmRoles": [
        "default-roles-techmarket-realm"
      ],
      "notBefore": 0,
      "groups": []
    }
  ],
  "scopeMappings": [
    {
      "clientScope": "offline_access",
      "roles": [
        "offline_access"
      ]
    }
  ],
  "clientScopeMappings": {
    "account": [
      {
        "client": "account-console",
        "roles": [
          "manage-account",
          "view-groups"
        ]
      }
    ]
  },
  "clients": [
    {
      "id": "1a69a001-5593-4d16-8160-c71531dc78a0",
      "clientId": "account",
      "name": "${client_account}",
      "rootUrl": "${authBaseUrl}",
      "baseUrl": "/realms/techmarket-realm/account/",
      "surrogateAuthRequired": false,
      "enabled": true,
      "alwaysDisplayInConsole": false,
      "clientAuthenticatorType": "client-secret",
      "redirectUris": [
        "/realms/techmarket-realm/account/*"
      ],
      "webOrigins": [],
      "notBefore": 0,
      "bearerOnly": false,
      "consentRequired": false,
      "standardFlowEnabled": true,
      "implicitFlowEnabled": false,
      "directAccessGrantsEnabled": false,
      "serviceAccountsEnabled": false,
      "publicClient": true,
      "frontchannelLogout": false,
      "protocol": "openid-connect",
      "attributes": {
        "realm_client": "false",
        "post.logout.redirect.uris": "+"
      },
      "authenticationFlowBindingOverrides": {},
      "fullScopeAllowed": false,
      "nodeReRegistrationTimeout": 0,
      "defaultClientScopes": [
        "web-origins",
        "acr",
        "roles",
        "profile",
        "basic",
        "email"
      ],
      "optionalClientScopes": [
        "address",
        "phone",
        "offline_access",
        "organization",
        "microprofile-jwt"
      ]
    },
    {
      "id": "c489506e-8951-4a1c-9378-2c89ac3a4324",
      "clientId": "account-console",
      "name": "${client_account-console}",
      "rootUrl": "${authBaseUrl}",
      "baseUrl": "/realms/techmarket-realm/account/",
      "surrogateAuthRequired": false,
      "enabled": true,
      "alwaysDisplayInConsole": false,
      "clientAuthenticatorType": "client-secret",
      "redirectUris": [
        "/realms/techmarket-realm/account/*"
      ],
      "webOrigins": [],
      "notBefore": 0,
      "bearerOnly": false,
      "consentRequired": false,
      "standardFlowEnabled": true,
      "implicitFlowEnabled": false,
      "directAccessGrantsEnabled": false,
      "serviceAccountsEnabled": false,
      "publicClient": true,
      "frontchannelLogout": false,
      "protocol": "openid-connect",
      "attributes": {
        "realm_client": "false",
        "post.logout.redirect.uris": "+",
        "pkce.code.challenge.method": "S256"
      },
      "authenticationFlowBindingOverrides": {},
      "fullScopeAllowed": false,
      "nodeReRegistrationTimeout": 0,
      "protocolMappers": [
        {
          "id": "e186cd9f-b116-4be5-8a02-dff0587c1c11",
          "name": "audience resolve",
          "protocol": "openid-connect",
          "protocolMapper": "oidc-audience-resolve-mapper",
          "consentRequired": false,
          "config": {}
        }
      ],
      "defaultClientScopes": [
        "web-origins",
        "acr",
        "roles",
        "profile",
        "basic",
        "email"
      ],
      "optionalClientScopes": [
        "address",
        "phone",
        "offline_access",
        "organization",
        "microprofile-jwt"
      ]
    },
    {
      "id": "4e1f4624-dab7-422d-b1ef-fef05425c678",
      "clientId": "admin-cli",
      "name": "${client_admin-cli}",
      "surrogateAuthRequired": false,
      "enabled": true,
      "alwaysDisplayInConsole": false,
      "clientAuthenticatorType": "client-secret",
      "redirectUris": [],
      "webOrigins": [],
      "notBefore": 0,
      "bearerOnly": false,
      "consentRequired": false,
      "standardFlowEnabled": false,
      "implicitFlowEnabled": false,
      "directAccessGrantsEnabled": true,
      "serviceAccountsEnabled": false,
      "publicClient": true,
      "frontchannelLogout": false,
      "protocol": "openid-connect",
      "attributes": {
        "realm_client": "false",
        "client.use.lightweight.access.token.enabled": "true"
      },
      "authenticationFlowBindingOverrides": {},
      "fullScopeAllowed": true,
      "nodeReRegistrationTimeout": 0,
      "defaultClientScopes": [
        "web-origins",
        "acr",
        "roles",
        "profile",
        "basic",
        "email"
      ],
      "optionalClientScopes": [
        "address",
        "phone",
        "offline_access",
        "organization",
        "microprofile-jwt"
      ]
    },
    {
      "id": "557b4cac-ca7f-4fff-a895-1545ee59b69a",
      "clientId": "broker",
      "name": "${client_broker}",
      "surrogateAuthRequired": false,
      "enabled": true,
      "alwaysDisplayInConsole": false,
      "clientAuthenticatorType": "client-secret",
      "redirectUris": [],
      "webOrigins": [],
      "notBefore": 0,
      "bearerOnly": true,
      "consentRequired": false,
      "standardFlowEnabled": true,
      "implicitFlowEnabled": false,
      "directAccessGrantsEnabled": false,
      "serviceAccountsEnabled": false,
      "publicClient": false,
      "frontchannelLogout": false,
      "protocol": "openid-connect",
      "attributes": {
        "realm_client": "true"
      },
      "authenticationFlowBindingOverrides": {},
      "fullScopeAllowed": false,
      "nodeReRegistrationTimeout": 0,
      "defaultClientScopes": [
        "web-origins",
        "acr",
        "roles",
        "profile",
        "basic",
        "email"
      ],
      "optionalClientScopes": [
        "address",
        "phone",
        "offline_access",
        "organization",
        "microprofile-jwt"
      ]
    },
    {
      "id": "f4f19fd1-87ce-40b0-afca-aefb080d2092",
      "clientId": "realm-management",
      "name": "${client_realm-management}",
      "surrogateAuthRequired": false,
      "enabled": true,
      "alwaysDisplayInConsole": false,
      "clientAuthenticatorType": "client-secret",
      "redirectUris": [],
      "webOrigins": [],
      "notBefore": 0,
      "bearerOnly": true,
      "consentRequired": false,
      "standardFlowEnabled": true,
      "implicitFlowEnabled": false,
      "directAccessGrantsEnabled": false,
      "serviceAccountsEnabled": false,
      "publicClient": false,
      "frontchannelLogout": false,
      "protocol": "openid-connect",
      "attributes": {
        "realm_client": "true"
      },
      "authenticationFlowBindingOverrides": {},
      "fullScopeAllowed": false,
      "nodeReRegistrationTimeout": 0,
      "defaultClientScopes": [
        "web-origins",
        "acr",
        "roles",
        "profile",
        "basic",
        "email"
      ],
      "optionalClientScopes": [
        "address",
        "phone",
        "offline_access",
        "organization",
        "microprofile-jwt"
      ]
    },
    {
      "id": "7fe40147-6d63-4210-8009-1776730b7de7",
      "clientId": "security-admin-console",
      "name": "${client_security-admin-console}",
      "rootUrl": "${authAdminUrl}",
      "baseUrl": "/admin/techmarket-realm/console/",
      "surrogateAuthRequired": false,
      "enabled": true,
      "alwaysDisplayInConsole": false,
      "clientAuthenticatorType": "client-secret",
      "redirectUris": [
        "/admin/techmarket-realm/console/*"
      ],
      "webOrigins": [
        "+"
      ],
      "notBefore": 0,
      "bearerOnly": false,
      "consentRequired": false,
      "standardFlowEnabled": true,
      "implicitFlowEnabled": false,
      "directAccessGrantsEnabled": false,
      "serviceAccountsEnabled": false,
      "publicClient": true,
      "frontchannelLogout": false,
      "protocol": "openid-connect",
      "attributes": {
        "realm_client": "false",
        "client.use.lightweight.access.token.enabled": "true",
        "post.logout.redirect.uris": "+",
        "pkce.code.challenge.method": "S256"
      },
      "authenticationFlowBindingOverrides": {},
      "fullScopeAllowed": true,
      "nodeReRegistrationTimeout": 0,
      "protocolMappers": [
        {
          "id": "fa4cbc3f-27f2-4c7a-8cab-232084457942",
          "name": "locale",
          "protocol": "openid-connect",
          "protocolMapper": "oidc-usermodel-attribute-mapper",
          "consentRequired": false,
          "config": {
            "introspection.token.claim": "true",
            "userinfo.token.claim": "true",
            "user.attribute": "locale",
            "id.token.claim": "true",
            "access.token.claim": "true",
            "claim.name": "locale",
            "jsonType.label": "String"
          }
        }
      ],
      "defaultClientScopes": [
        "web-origins",
        "acr",
        "roles",
        "profile",
        "basic",
        "email"
      ],
      "optionalClientScopes": [
        "address",
        "phone",
        "offline_access",
        "organization",
        "microprofile-jwt"
      ]
    },
    {
      "id": "089a490c-7256-489c-b850-f9c48c8d1a45",
      "clientId": "techmarket-client",
      "name": "",
      "description": "",
      "rootUrl": "",
      "adminUrl": "",
      "baseUrl": "",
      "surrogateAuthRequired": false,
      "enabled": true,
      "alwaysDisplayInConsole": false,
      "clientAuthenticatorType": "client-secret",
      "secret": "**********",
      "redirectUris": [
        ""
      ],
      "webOrigins": [
        ""
      ],
      "notBefore": 0,
      "bearerOnly": false,
      "consentRequired": false,
      "standardFlowEnabled": true,
      "implicitFlowEnabled": false,
      "directAccessGrantsEnabled": true,
      "serviceAccountsEnabled": true,
      "publicClient": false,
      "frontchannelLogout": true,
      "protocol": "openid-connect",
      "attributes": {
        "logout.confirmation.enabled": "false",
        "realm_client": "false",
        "oidc.ciba.grant.enabled": "false",
        "client.secret.creation.time": "1776004511",
        "backchannel.logout.session.required": "true",
        "oauth2.jwt.authorization.grant.enabled": "false",
        "standard.token.exchange.enabled": "false",
        "frontchannel.logout.session.required": "true",
        "display.on.consent.screen": "false",
        "oauth2.device.authorization.grant.enabled": "false",
        "backchannel.logout.revoke.offline.tokens": "false",
        "dpop.bound.access.tokens": "false"
      },
      "authenticationFlowBindingOverrides": {},
      "fullScopeAllowed": true,
      "nodeReRegistrationTimeout": -1,
      "defaultClientScopes": [
        "web-origins",
        "service_account",
        "acr",
        "roles",
        "profile",
        "basic",
        "email"
      ],
      "optionalClientScopes": [
        "address",
        "phone",
        "offline_access",
        "organization",
        "microprofile-jwt"
      ]
    }
  ],
  "clientScopes": [
    {
      "id": "88a261bc-3374-4bcb-82e5-7b9cc4b1f4cb",
      "name": "address",
      "description": "OpenID Connect built-in scope: address",
      "protocol": "openid-connect",
      "attributes": {
        "include.in.token.scope": "true",
        "consent.screen.text": "${addressScopeConsentText}",
        "display.on.consent.screen": "true"
      },
      "protocolMappers": [
        {
          "id": "98ace498-bd59-4242-99cb-e368df17759c",
          "name": "address",
          "protocol": "openid-connect",
          "protocolMapper": "oidc-address-mapper",
          "consentRequired": false,
          "config": {
            "user.attribute.formatted": "formatted",
            "user.attribute.country": "country",
            "introspection.token.claim": "true",
            "user.attribute.postal_code": "postal_code",
            "userinfo.token.claim": "true",
            "user.attribute.street": "street",
            "id.token.claim": "true",
            "user.attribute.region": "region",
            "access.token.claim": "true",
            "user.attribute.locality": "locality"
          }
        }
      ]
    },
    {
      "id": "8b8b814e-2841-4c64-9ab3-eb4d4e9ef2c6",
      "name": "saml_organization",
      "description": "Organization Membership",
      "protocol": "saml",
      "attributes": {
        "display.on.consent.screen": "false"
      },
      "protocolMappers": [
        {
          "id": "8e1dcb96-e594-413b-9f91-941c8ab02977",
          "name": "organization",
          "protocol": "saml",
          "protocolMapper": "saml-organization-membership-mapper",
          "consentRequired": false,
          "config": {}
        }
      ]
    },
    {
      "id": "4de514af-b0f5-4f0d-9912-d83cbdc67e6c",
      "name": "role_list",
      "description": "SAML role list",
      "protocol": "saml",
      "attributes": {
        "consent.screen.text": "${samlRoleListScopeConsentText}",
        "display.on.consent.screen": "true"
      },
      "protocolMappers": [
        {
          "id": "4df59297-a0e6-44f2-9e84-c808d4658098",
          "name": "role list",
          "protocol": "saml",
          "protocolMapper": "saml-role-list-mapper",
          "consentRequired": false,
          "config": {
            "single": "false",
            "attribute.nameformat": "Basic",
            "attribute.name": "Role"
          }
        }
      ]
    },
    {
      "id": "fa6c6f54-d55a-4c3e-a424-5015e536a43f",
      "name": "profile",
      "description": "OpenID Connect built-in scope: profile",
      "protocol": "openid-connect",
      "attributes": {
        "include.in.token.scope": "true",
        "consent.screen.text": "${profileScopeConsentText}",
        "display.on.consent.screen": "true"
      },
      "protocolMappers": [
        {
          "id": "d26f370e-423b-4203-aeee-a59a568b12bd",
          "name": "full name",
          "protocol": "openid-connect",
          "protocolMapper": "oidc-full-name-mapper",
          "consentRequired": false,
          "config": {
            "id.token.claim": "true",
            "access.token.claim": "true",
            "introspection.token.claim": "true",
            "userinfo.token.claim": "true"
          }
        },
        {
          "id": "422789f6-05d2-46e8-abf1-e9c52ba780c3",
          "name": "family name",
          "protocol": "openid-connect",
          "protocolMapper": "oidc-usermodel-attribute-mapper",
          "consentRequired": false,
          "config": {
            "introspection.token.claim": "true",
            "userinfo.token.claim": "true",
            "user.attribute": "lastName",
            "id.token.claim": "true",
            "access.token.claim": "true",
            "claim.name": "family_name",
            "jsonType.label": "String"
          }
        },
        {
          "id": "2252f7e4-1c89-435b-be5b-192525dc6173",
          "name": "locale",
          "protocol": "openid-connect",
          "protocolMapper": "oidc-usermodel-attribute-mapper",
          "consentRequired": false,
          "config": {
            "introspection.token.claim": "true",
            "userinfo.token.claim": "true",
            "user.attribute": "locale",
            "id.token.claim": "true",
            "access.token.claim": "true",
            "claim.name": "locale",
            "jsonType.label": "String"
          }
        },
        {
          "id": "4b49f8cf-d095-4818-bcdf-ba40168dc0f0",
          "name": "zoneinfo",
          "protocol": "openid-connect",
          "protocolMapper": "oidc-usermodel-attribute-mapper",
          "consentRequired": false,
          "config": {
            "introspection.token.claim": "true",
            "userinfo.token.claim": "true",
            "user.attribute": "zoneinfo",
            "id.token.claim": "true",
            "access.token.claim": "true",
            "claim.name": "zoneinfo",
            "jsonType.label": "String"
          }
        },
        {
          "id": "8c4bd7be-777a-447c-9959-55e646aebf5b",
          "name": "website",
          "protocol": "openid-connect",
          "protocolMapper": "oidc-usermodel-attribute-mapper",
          "consentRequired": false,
          "config": {
            "introspection.token.claim": "true",
            "userinfo.token.claim": "true",
            "user.attribute": "website",
            "id.token.claim": "true",
            "access.token.claim": "true",
            "claim.name": "website",
            "jsonType.label": "String"
          }
        },
        {
          "id": "f4d919e3-50ec-46d0-8273-46ef7cab2674",
          "name": "profile",
          "protocol": "openid-connect",
          "protocolMapper": "oidc-usermodel-attribute-mapper",
          "consentRequired": false,
          "config": {
            "introspection.token.claim": "true",
            "userinfo.token.claim": "true",
            "user.attribute": "profile",
            "id.token.claim": "true",
            "access.token.claim": "true",
            "claim.name": "profile",
            "jsonType.label": "String"
          }
        },
        {
          "id": "34d92d56-5db6-4324-8386-05346c47fdda",
          "name": "gender",
          "protocol": "openid-connect",
          "protocolMapper": "oidc-usermodel-attribute-mapper",
          "consentRequired": false,
          "config": {
            "introspection.token.claim": "true",
            "userinfo.token.claim": "true",
            "user.attribute": "gender",
            "id.token.claim": "true",
            "access.token.claim": "true",
            "claim.name": "gender",
            "jsonType.label": "String"
          }
        },
        {
          "id": "5237202d-cf6f-4dba-914e-0b55fa385f26",
          "name": "given name",
          "protocol": "openid-connect",
          "protocolMapper": "oidc-usermodel-attribute-mapper",
          "consentRequired": false,
          "config": {
            "introspection.token.claim": "true",
            "userinfo.token.claim": "true",
            "user.attribute": "firstName",
            "id.token.claim": "true",
            "access.token.claim": "true",
            "claim.name": "given_name",
            "jsonType.label": "String"
          }
        },
        {
          "id": "258addfd-9353-4f6a-b37e-a856da4b72e1",
          "name": "picture",
          "protocol": "openid-connect",
          "protocolMapper": "oidc-usermodel-attribute-mapper",
          "consentRequired": false,
          "config": {
            "introspection.token.claim": "true",
            "userinfo.token.claim": "true",
            "user.attribute": "picture",
            "id.token.claim": "true",
            "access.token.claim": "true",
            "claim.name": "picture",
            "jsonType.label": "String"
          }
        },
        {
          "id": "bb340155-f99e-4abd-81f7-725d523a0a5b",
          "name": "nickname",
          "protocol": "openid-connect",
          "protocolMapper": "oidc-usermodel-attribute-mapper",
          "consentRequired": false,
          "config": {
            "introspection.token.claim": "true",
            "userinfo.token.claim": "true",
            "user.attribute": "nickname",
            "id.token.claim": "true",
            "access.token.claim": "true",
            "claim.name": "nickname",
            "jsonType.label": "String"
          }
        },
        {
          "id": "a661fba2-ed2e-4eac-be35-be34e5729c8c",
          "name": "updated at",
          "protocol": "openid-connect",
          "protocolMapper": "oidc-usermodel-attribute-mapper",
          "consentRequired": false,
          "config": {
            "introspection.token.claim": "true",
            "userinfo.token.claim": "true",
            "user.attribute": "updatedAt",
            "id.token.claim": "true",
            "access.token.claim": "true",
            "claim.name": "updated_at",
            "jsonType.label": "long"
          }
        },
        {
          "id": "d5a2b6a0-881d-49df-b874-a33630b0b380",
          "name": "birthdate",
          "protocol": "openid-connect",
          "protocolMapper": "oidc-usermodel-attribute-mapper",
          "consentRequired": false,
          "config": {
            "introspection.token.claim": "true",
            "userinfo.token.claim": "true",
            "user.attribute": "birthdate",
            "id.token.claim": "true",
            "access.token.claim": "true",
            "claim.name": "birthdate",
            "jsonType.label": "String"
          }
        },
        {
          "id": "1e4057ff-def7-47d3-903a-5a6c642db69f",
          "name": "middle name",
          "protocol": "openid-connect",
          "protocolMapper": "oidc-usermodel-attribute-mapper",
          "consentRequired": false,
          "config": {
            "introspection.token.claim": "true",
            "userinfo.token.claim": "true",
            "user.attribute": "middleName",
            "id.token.claim": "true",
            "access.token.claim": "true",
            "claim.name": "middle_name",
            "jsonType.label": "String"
          }
        },
        {
          "id": "e12f13c8-5f05-4015-bb18-6dc67598a1a1",
          "name": "username",
          "protocol": "openid-connect",
          "protocolMapper": "oidc-usermodel-attribute-mapper",
          "consentRequired": false,
          "config": {
            "introspection.token.claim": "true",
            "userinfo.token.claim": "true",
            "user.attribute": "username",
            "id.token.claim": "true",
            "access.token.claim": "true",
            "claim.name": "preferred_username",
            "jsonType.label": "String"
          }
        }
      ]
    },
    {
      "id": "70919102-8b0d-4b27-ab25-bf135db08480",
      "name": "microprofile-jwt",
      "description": "Microprofile - JWT built-in scope",
      "protocol": "openid-connect",
      "attributes": {
        "include.in.token.scope": "true",
        "display.on.consent.screen": "false"
      },
      "protocolMappers": [
        {
          "id": "1ad4e69d-fff7-4c93-9b13-4391056cb80e",
          "name": "groups",
          "protocol": "openid-connect",
          "protocolMapper": "oidc-usermodel-realm-role-mapper",
          "consentRequired": false,
          "config": {
            "introspection.token.claim": "true",
            "multivalued": "true",
            "user.attribute": "foo",
            "id.token.claim": "true",
            "access.token.claim": "true",
            "claim.name": "groups",
            "jsonType.label": "String"
          }
        },
        {
          "id": "06d9478d-ee39-43fe-beb0-e7ab22784993",
          "name": "upn",
          "protocol": "openid-connect",
          "protocolMapper": "oidc-usermodel-attribute-mapper",
          "consentRequired": false,
          "config": {
            "introspection.token.claim": "true",
            "userinfo.token.claim": "true",
            "user.attribute": "username",
            "id.token.claim": "true",
            "access.token.claim": "true",
            "claim.name": "upn",
            "jsonType.label": "String"
          }
        }
      ]
    },
    {
      "id": "3fa75095-1109-40a2-baf3-d5369be75ac9",
      "name": "web-origins",
      "description": "OpenID Connect scope for add allowed web origins to the access token",
      "protocol": "openid-connect",
      "attributes": {
        "include.in.token.scope": "false",
        "consent.screen.text": "",
        "display.on.consent.screen": "false"
      },
      "protocolMappers": [
        {
          "id": "4299f6e4-1910-4069-8474-f7a4d947b1dd",
          "name": "allowed web origins",
          "protocol": "openid-connect",
          "protocolMapper": "oidc-allowed-origins-mapper",
          "consentRequired": false,
          "config": {
            "access.token.claim": "true",
            "introspection.token.claim": "true"
          }
        }
      ]
    },
    {
      "id": "defb1fe1-82f5-47ff-a17e-6e406c266b98",
      "name": "service_account",
      "description": "Specific scope for a client enabled for service accounts",
      "protocol": "openid-connect",
      "attributes": {
        "include.in.token.scope": "false",
        "display.on.consent.screen": "false"
      },
      "protocolMappers": [
        {
          "id": "421b424e-74d4-4c21-9e84-7ae459cf0bfa",
          "name": "Client ID",
          "protocol": "openid-connect",
          "protocolMapper": "oidc-usersessionmodel-note-mapper",
          "consentRequired": false,
          "config": {
            "user.session.note": "client_id",
            "id.token.claim": "true",
            "introspection.token.claim": "true",
            "access.token.claim": "true",
            "claim.name": "client_id",
            "jsonType.label": "String"
          }
        },
        {
          "id": "b31fba77-6f24-485f-982a-85f19e3e386d",
          "name": "Client Host",
          "protocol": "openid-connect",
          "protocolMapper": "oidc-usersessionmodel-note-mapper",
          "consentRequired": false,
          "config": {
            "user.session.note": "clientHost",
            "id.token.claim": "true",
            "introspection.token.claim": "true",
            "access.token.claim": "true",
            "claim.name": "clientHost",
            "jsonType.label": "String"
          }
        },
        {
          "id": "292211b2-c365-4ed0-b858-fa2e27e1f592",
          "name": "Client IP Address",
          "protocol": "openid-connect",
          "protocolMapper": "oidc-usersessionmodel-note-mapper",
          "consentRequired": false,
          "config": {
            "user.session.note": "clientAddress",
            "id.token.claim": "true",
            "introspection.token.claim": "true",
            "access.token.claim": "true",
            "claim.name": "clientAddress",
            "jsonType.label": "String"
          }
        }
      ]
    },
    {
      "id": "2fcdeb1a-ec76-48ac-9cfb-328ab771bd55",
      "name": "email",
      "description": "OpenID Connect built-in scope: email",
      "protocol": "openid-connect",
      "attributes": {
        "include.in.token.scope": "true",
        "consent.screen.text": "${emailScopeConsentText}",
        "display.on.consent.screen": "true"
      },
      "protocolMappers": [
        {
          "id": "6283621c-b7a1-4be7-980d-f1aa986ad707",
          "name": "email verified",
          "protocol": "openid-connect",
          "protocolMapper": "oidc-usermodel-property-mapper",
          "consentRequired": false,
          "config": {
            "introspection.token.claim": "true",
            "userinfo.token.claim": "true",
            "user.attribute": "emailVerified",
            "id.token.claim": "true",
            "access.token.claim": "true",
            "claim.name": "email_verified",
            "jsonType.label": "boolean"
          }
        },
        {
          "id": "ee724a01-188e-4df2-aa8c-4e3daf1e99f3",
          "name": "email",
          "protocol": "openid-connect",
          "protocolMapper": "oidc-usermodel-attribute-mapper",
          "consentRequired": false,
          "config": {
            "introspection.token.claim": "true",
            "userinfo.token.claim": "true",
            "user.attribute": "email",
            "id.token.claim": "true",
            "access.token.claim": "true",
            "claim.name": "email",
            "jsonType.label": "String"
          }
        }
      ]
    },
    {
      "id": "965bf93e-c9e9-44eb-88c3-2f600144caaf",
      "name": "acr",
      "description": "OpenID Connect scope for add acr (authentication context class reference) to the token",
      "protocol": "openid-connect",
      "attributes": {
        "include.in.token.scope": "false",
        "display.on.consent.screen": "false"
      },
      "protocolMappers": [
        {
          "id": "c6fb7b86-2a2a-47e1-8ea4-a4917ed7b069",
          "name": "acr loa level",
          "protocol": "openid-connect",
          "protocolMapper": "oidc-acr-mapper",
          "consentRequired": false,
          "config": {
            "id.token.claim": "true",
            "access.token.claim": "true",
            "introspection.token.claim": "true"
          }
        }
      ]
    },
    {
      "id": "9976fac6-cd45-478c-92a3-ad9c9f1b7097",
      "name": "roles",
      "description": "OpenID Connect scope for add user roles to the access token",
      "protocol": "openid-connect",
      "attributes": {
        "include.in.token.scope": "false",
        "consent.screen.text": "${rolesScopeConsentText}",
        "display.on.consent.screen": "true"
      },
      "protocolMappers": [
        {
          "id": "f567a39f-ec53-4110-a30a-2a29a8b9105a",
          "name": "client roles",
          "protocol": "openid-connect",
          "protocolMapper": "oidc-usermodel-client-role-mapper",
          "consentRequired": false,
          "config": {
            "user.attribute": "foo",
            "introspection.token.claim": "true",
            "access.token.claim": "true",
            "claim.name": "resource_access.${client_id}.roles",
            "jsonType.label": "String",
            "multivalued": "true"
          }
        },
        {
          "id": "4f3293ae-567a-427e-8571-9938c4ece7ca",
          "name": "realm roles",
          "protocol": "openid-connect",
          "protocolMapper": "oidc-usermodel-realm-role-mapper",
          "consentRequired": false,
          "config": {
            "user.attribute": "foo",
            "introspection.token.claim": "true",
            "access.token.claim": "true",
            "claim.name": "realm_access.roles",
            "jsonType.label": "String",
            "multivalued": "true"
          }
        },
        {
          "id": "97585846-5ec7-4572-94b5-bd445d963085",
          "name": "audience resolve",
          "protocol": "openid-connect",
          "protocolMapper": "oidc-audience-resolve-mapper",
          "consentRequired": false,
          "config": {
            "access.token.claim": "true",
            "introspection.token.claim": "true"
          }
        }
      ]
    },
    {
      "id": "61a06f08-c167-44c2-8425-f51e22a2cf9a",
      "name": "offline_access",
      "description": "OpenID Connect built-in scope: offline_access",
      "protocol": "openid-connect",
      "attributes": {
        "consent.screen.text": "${offlineAccessScopeConsentText}",
        "display.on.consent.screen": "true"
      }
    },
    {
      "id": "dc83e910-65dc-4071-9e6b-8e7f573e4909",
      "name": "organization",
      "description": "Additional claims about the organization a subject belongs to",
      "protocol": "openid-connect",
      "attributes": {
        "include.in.token.scope": "true",
        "consent.screen.text": "${organizationScopeConsentText}",
        "display.on.consent.screen": "true"
      },
      "protocolMappers": [
        {
          "id": "13058a45-6f3d-4f7b-b040-d64f909208d3",
          "name": "organization",
          "protocol": "openid-connect",
          "protocolMapper": "oidc-organization-membership-mapper",
          "consentRequired": false,
          "config": {
            "id.token.claim": "true",
            "introspection.token.claim": "true",
            "access.token.claim": "true",
            "claim.name": "organization",
            "jsonType.label": "String",
            "multivalued": "true"
          }
        }
      ]
    },
    {
      "id": "320b0024-d5e5-4073-84cc-fde92cc5e8ca",
      "name": "basic",
      "description": "OpenID Connect scope for add all basic claims to the token",
      "protocol": "openid-connect",
      "attributes": {
        "include.in.token.scope": "false",
        "display.on.consent.screen": "false"
      },
      "protocolMappers": [
        {
          "id": "42905e0b-e710-46eb-a7a2-7ffa1b78c5a7",
          "name": "sub",
          "protocol": "openid-connect",
          "protocolMapper": "oidc-sub-mapper",
          "consentRequired": false,
          "config": {
            "access.token.claim": "true",
            "introspection.token.claim": "true"
          }
        },
        {
          "id": "e9a7ecd3-0a44-41d7-961c-d47cf46250e8",
          "name": "auth_time",
          "protocol": "openid-connect",
          "protocolMapper": "oidc-usersessionmodel-note-mapper",
          "consentRequired": false,
          "config": {
            "user.session.note": "AUTH_TIME",
            "id.token.claim": "true",
            "introspection.token.claim": "true",
            "access.token.claim": "true",
            "claim.name": "auth_time",
            "jsonType.label": "long"
          }
        }
      ]
    },
    {
      "id": "6c5bf72f-8939-46d4-981f-84ef82e674ce",
      "name": "phone",
      "description": "OpenID Connect built-in scope: phone",
      "protocol": "openid-connect",
      "attributes": {
        "include.in.token.scope": "true",
        "consent.screen.text": "${phoneScopeConsentText}",
        "display.on.consent.screen": "true"
      },
      "protocolMappers": [
        {
          "id": "494d87a1-0060-4329-bc26-a3d23cd1f780",
          "name": "phone number verified",
          "protocol": "openid-connect",
          "protocolMapper": "oidc-usermodel-attribute-mapper",
          "consentRequired": false,
          "config": {
            "introspection.token.claim": "true",
            "userinfo.token.claim": "true",
            "user.attribute": "phoneNumberVerified",
            "id.token.claim": "true",
            "access.token.claim": "true",
            "claim.name": "phone_number_verified",
            "jsonType.label": "boolean"
          }
        },
        {
          "id": "a7956c12-4474-4305-81de-9d4c610a26b7",
          "name": "phone number",
          "protocol": "openid-connect",
          "protocolMapper": "oidc-usermodel-attribute-mapper",
          "consentRequired": false,
          "config": {
            "introspection.token.claim": "true",
            "userinfo.token.claim": "true",
            "user.attribute": "phoneNumber",
            "id.token.claim": "true",
            "access.token.claim": "true",
            "claim.name": "phone_number",
            "jsonType.label": "String"
          }
        }
      ]
    }
  ],
  "defaultDefaultClientScopes": [
    "email",
    "basic",
    "web-origins",
    "role_list",
    "saml_organization",
    "acr",
    "roles",
    "profile"
  ],
  "defaultOptionalClientScopes": [
    "offline_access",
    "phone",
    "microprofile-jwt",
    "address",
    "organization"
  ],
  "browserSecurityHeaders": {
    "contentSecurityPolicyReportOnly": "",
    "xContentTypeOptions": "nosniff",
    "referrerPolicy": "no-referrer",
    "xRobotsTag": "none",
    "xFrameOptions": "SAMEORIGIN",
    "contentSecurityPolicy": "frame-src 'self'; frame-ancestors 'self'; object-src 'none';",
    "strictTransportSecurity": "max-age=31536000; includeSubDomains"
  },
  "smtpServer": {},
  "eventsEnabled": false,
  "eventsListeners": [
    "jboss-logging"
  ],
  "enabledEventTypes": [],
  "adminEventsEnabled": false,
  "adminEventsDetailsEnabled": false,
  "identityProviders": [],
  "identityProviderMappers": [],
  "components": {
    "org.keycloak.services.clientregistration.policy.ClientRegistrationPolicy": [
      {
        "id": "cd008319-bb4b-4ee7-817a-fc40d76d27f9",
        "name": "Full Scope Disabled",
        "providerId": "scope",
        "subType": "anonymous",
        "subComponents": {},
        "config": {}
      },
      {
        "id": "110d7478-8834-432e-bdfa-c6bfa22e237a",
        "name": "Allowed Client Scopes",
        "providerId": "allowed-client-templates",
        "subType": "authenticated",
        "subComponents": {},
        "config": {
          "allow-default-scopes": [
            "true"
          ]
        }
      },
      {
        "id": "8c207090-8ffb-48d8-8c9c-be19e7bea729",
        "name": "Allowed Protocol Mapper Types",
        "providerId": "allowed-protocol-mappers",
        "subType": "authenticated",
        "subComponents": {},
        "config": {
          "allowed-protocol-mapper-types": [
            "oidc-sha256-pairwise-sub-mapper",
            "oidc-usermodel-attribute-mapper",
            "oidc-full-name-mapper",
            "oidc-address-mapper",
            "saml-role-list-mapper",
            "oidc-usermodel-property-mapper",
            "saml-user-property-mapper",
            "saml-user-attribute-mapper"
          ]
        }
      },
      {
        "id": "b537acd8-48ce-4553-aa37-ed76dae865c6",
        "name": "Consent Required",
        "providerId": "consent-required",
        "subType": "anonymous",
        "subComponents": {},
        "config": {}
      },
      {
        "id": "ea8959ce-c04d-468a-9b48-d71075cbac09",
        "name": "Allowed Protocol Mapper Types",
        "providerId": "allowed-protocol-mappers",
        "subType": "anonymous",
        "subComponents": {},
        "config": {
          "allowed-protocol-mapper-types": [
            "oidc-full-name-mapper",
            "oidc-usermodel-property-mapper",
            "oidc-sha256-pairwise-sub-mapper",
            "saml-role-list-mapper",
            "saml-user-attribute-mapper",
            "oidc-address-mapper",
            "oidc-usermodel-attribute-mapper",
            "saml-user-property-mapper"
          ]
        }
      },
      {
        "id": "49e53082-7338-4bfa-bd5a-4ec912b45a8c",
        "name": "Max Clients Limit",
        "providerId": "max-clients",
        "subType": "anonymous",
        "subComponents": {},
        "config": {
          "max-clients": [
            "200"
          ]
        }
      },
      {
        "id": "8d25eff7-80ba-4dac-8371-da9258353bcc",
        "name": "Trusted Hosts",
        "providerId": "trusted-hosts",
        "subType": "anonymous",
        "subComponents": {},
        "config": {
          "host-sending-registration-request-must-match": [
            "true"
          ],
          "client-uris-must-match": [
            "true"
          ]
        }
      },
      {
        "id": "f4e72323-75e0-437d-b19c-deba8644661f",
        "name": "Allowed Client Scopes",
        "providerId": "allowed-client-templates",
        "subType": "anonymous",
        "subComponents": {},
        "config": {
          "allow-default-scopes": [
            "true"
          ]
        }
      },
      {
        "id": "a251da71-e98e-421f-af07-5540c1f2d9f6",
        "name": "Allowed Registration Web Origins",
        "providerId": "registration-web-origins",
        "subType": "anonymous",
        "subComponents": {},
        "config": {}
      },
      {
        "id": "63419771-ff6a-4899-a7dd-cad1a44ddadb",
        "name": "Allowed Registration Web Origins",
        "providerId": "registration-web-origins",
        "subType": "authenticated",
        "subComponents": {},
        "config": {}
      }
    ],
    "org.keycloak.keys.KeyProvider": [
      {
        "id": "ab0e20a9-55fa-4d5e-8baf-a3f41fe8445f",
        "name": "rsa-generated",
        "providerId": "rsa-generated",
        "subComponents": {},
        "config": {
          "priority": [
            "100"
          ]
        }
      },
      {
        "id": "0240bb4a-4d11-4140-b8e2-a978f621460c",
        "name": "aes-generated",
        "providerId": "aes-generated",
        "subComponents": {},
        "config": {
          "priority": [
            "100"
          ]
        }
      },
      {
        "id": "17908bc8-fc59-48d5-af49-ead4f375d286",
        "name": "rsa-enc-generated",
        "providerId": "rsa-enc-generated",
        "subComponents": {},
        "config": {
          "priority": [
            "100"
          ],
          "algorithm": [
            "RSA-OAEP"
          ]
        }
      },
      {
        "id": "fa229736-c0cb-4d81-8ab7-5df4e2f6e719",
        "name": "hmac-generated-hs512",
        "providerId": "hmac-generated",
        "subComponents": {},
        "config": {
          "priority": [
            "100"
          ],
          "algorithm": [
            "HS512"
          ]
        }
      }
    ]
  },
  "internationalizationEnabled": false,
  "authenticationFlows": [
    {
      "id": "6c07d477-0390-4032-b457-e9986d6c7ec8",
      "alias": "Account verification options",
      "description": "Method with which to verify the existing account",
      "providerId": "basic-flow",
      "topLevel": false,
      "builtIn": true,
      "authenticationExecutions": [
        {
          "authenticator": "idp-email-verification",
          "authenticatorFlow": false,
          "requirement": "ALTERNATIVE",
          "priority": 10,
          "autheticatorFlow": false,
          "userSetupAllowed": false
        },
        {
          "authenticatorFlow": true,
          "requirement": "ALTERNATIVE",
          "priority": 20,
          "autheticatorFlow": true,
          "flowAlias": "Verify Existing Account by Re-authentication",
          "userSetupAllowed": false
        }
      ]
    },
    {
      "id": "a13a3ef4-97dc-4d47-bb5c-367aff859d84",
      "alias": "Browser - Conditional 2FA",
      "description": "Flow to determine if any 2FA is required for the authentication",
      "providerId": "basic-flow",
      "topLevel": false,
      "builtIn": true,
      "authenticationExecutions": [
        {
          "authenticator": "conditional-user-configured",
          "authenticatorFlow": false,
          "requirement": "REQUIRED",
          "priority": 10,
          "autheticatorFlow": false,
          "userSetupAllowed": false
        },
        {
          "authenticatorConfig": "browser-conditional-credential",
          "authenticator": "conditional-credential",
          "authenticatorFlow": false,
          "requirement": "REQUIRED",
          "priority": 20,
          "autheticatorFlow": false,
          "userSetupAllowed": false
        },
        {
          "authenticator": "auth-otp-form",
          "authenticatorFlow": false,
          "requirement": "ALTERNATIVE",
          "priority": 30,
          "autheticatorFlow": false,
          "userSetupAllowed": false
        },
        {
          "authenticator": "webauthn-authenticator",
          "authenticatorFlow": false,
          "requirement": "DISABLED",
          "priority": 40,
          "autheticatorFlow": false,
          "userSetupAllowed": false
        },
        {
          "authenticator": "auth-recovery-authn-code-form",
          "authenticatorFlow": false,
          "requirement": "DISABLED",
          "priority": 50,
          "autheticatorFlow": false,
          "userSetupAllowed": false
        }
      ]
    },
    {
      "id": "65e7b358-bc24-4804-9631-5a444529519f",
      "alias": "Browser - Conditional Organization",
      "description": "Flow to determine if the organization identity-first login is to be used",
      "providerId": "basic-flow",
      "topLevel": false,
      "builtIn": true,
      "authenticationExecutions": [
        {
          "authenticator": "conditional-user-configured",
          "authenticatorFlow": false,
          "requirement": "REQUIRED",
          "priority": 10,
          "autheticatorFlow": false,
          "userSetupAllowed": false
        },
        {
          "authenticator": "organization",
          "authenticatorFlow": false,
          "requirement": "ALTERNATIVE",
          "priority": 20,
          "autheticatorFlow": false,
          "userSetupAllowed": false
        }
      ]
    },
    {
      "id": "ef4ac0d2-f3a7-4080-88a4-e906a976ed11",
      "alias": "Direct Grant - Conditional OTP",
      "description": "Flow to determine if the OTP is required for the authentication",
      "providerId": "basic-flow",
      "topLevel": false,
      "builtIn": true,
      "authenticationExecutions": [
        {
          "authenticator": "conditional-user-configured",
          "authenticatorFlow": false,
          "requirement": "REQUIRED",
          "priority": 10,
          "autheticatorFlow": false,
          "userSetupAllowed": false
        },
        {
          "authenticator": "direct-grant-validate-otp",
          "authenticatorFlow": false,
          "requirement": "REQUIRED",
          "priority": 20,
          "autheticatorFlow": false,
          "userSetupAllowed": false
        }
      ]
    },
    {
      "id": "a746723e-ad98-42e9-8d73-2d762816e8d5",
      "alias": "First Broker Login - Conditional Organization",
      "description": "Flow to determine if the authenticator that adds organization members is to be used",
      "providerId": "basic-flow",
      "topLevel": false,
      "builtIn": true,
      "authenticationExecutions": [
        {
          "authenticator": "conditional-user-configured",
          "authenticatorFlow": false,
          "requirement": "REQUIRED",
          "priority": 10,
          "autheticatorFlow": false,
          "userSetupAllowed": false
        },
        {
          "authenticator": "idp-add-organization-member",
          "authenticatorFlow": false,
          "requirement": "REQUIRED",
          "priority": 20,
          "autheticatorFlow": false,
          "userSetupAllowed": false
        }
      ]
    },
    {
      "id": "aa93c8eb-3d51-40e1-b291-f1c433641891",
      "alias": "First broker login - Conditional 2FA",
      "description": "Flow to determine if any 2FA is required for the authentication",
      "providerId": "basic-flow",
      "topLevel": false,
      "builtIn": true,
      "authenticationExecutions": [
        {
          "authenticator": "conditional-user-configured",
          "authenticatorFlow": false,
          "requirement": "REQUIRED",
          "priority": 10,
          "autheticatorFlow": false,
          "userSetupAllowed": false
        },
        {
          "authenticatorConfig": "first-broker-login-conditional-credential",
          "authenticator": "conditional-credential",
          "authenticatorFlow": false,
          "requirement": "REQUIRED",
          "priority": 20,
          "autheticatorFlow": false,
          "userSetupAllowed": false
        },
        {
          "authenticator": "auth-otp-form",
          "authenticatorFlow": false,
          "requirement": "ALTERNATIVE",
          "priority": 30,
          "autheticatorFlow": false,
          "userSetupAllowed": false
        },
        {
          "authenticator": "webauthn-authenticator",
          "authenticatorFlow": false,
          "requirement": "DISABLED",
          "priority": 40,
          "autheticatorFlow": false,
          "userSetupAllowed": false
        },
        {
          "authenticator": "auth-recovery-authn-code-form",
          "authenticatorFlow": false,
          "requirement": "DISABLED",
          "priority": 50,
          "autheticatorFlow": false,
          "userSetupAllowed": false
        }
      ]
    },
    {
      "id": "548d84be-c7d5-4c80-8704-7c834a5f8f98",
      "alias": "Handle Existing Account",
      "description": "Handle what to do if there is existing account with same email/username like authenticated identity provider",
      "providerId": "basic-flow",
      "topLevel": false,
      "builtIn": true,
      "authenticationExecutions": [
        {
          "authenticator": "idp-confirm-link",
          "authenticatorFlow": false,
          "requirement": "REQUIRED",
          "priority": 10,
          "autheticatorFlow": false,
          "userSetupAllowed": false
        },
        {
          "authenticatorFlow": true,
          "requirement": "REQUIRED",
          "priority": 20,
          "autheticatorFlow": true,
          "flowAlias": "Account verification options",
          "userSetupAllowed": false
        }
      ]
    },
    {
      "id": "ff532534-605e-4966-927f-6a6ef1de5bb6",
      "alias": "Organization",
      "providerId": "basic-flow",
      "topLevel": false,
      "builtIn": true,
      "authenticationExecutions": [
        {
          "authenticatorFlow": true,
          "requirement": "CONDITIONAL",
          "priority": 10,
          "autheticatorFlow": true,
          "flowAlias": "Browser - Conditional Organization",
          "userSetupAllowed": false
        }
      ]
    },
    {
      "id": "09cba1f8-b790-4c07-bacf-5ee1314d51f0",
      "alias": "Reset - Conditional OTP",
      "description": "Flow to determine if the OTP should be reset or not. Set to REQUIRED to force.",
      "providerId": "basic-flow",
      "topLevel": false,
      "builtIn": true,
      "authenticationExecutions": [
        {
          "authenticator": "conditional-user-configured",
          "authenticatorFlow": false,
          "requirement": "REQUIRED",
          "priority": 10,
          "autheticatorFlow": false,
          "userSetupAllowed": false
        },
        {
          "authenticator": "reset-otp",
          "authenticatorFlow": false,
          "requirement": "REQUIRED",
          "priority": 20,
          "autheticatorFlow": false,
          "userSetupAllowed": false
        }
      ]
    },
    {
      "id": "344ace8f-740b-4d31-b733-430a6fb04bb6",
      "alias": "User creation or linking",
      "description": "Flow for the existing/non-existing user alternatives",
      "providerId": "basic-flow",
      "topLevel": false,
      "builtIn": true,
      "authenticationExecutions": [
        {
          "authenticatorConfig": "create unique user config",
          "authenticator": "idp-create-user-if-unique",
          "authenticatorFlow": false,
          "requirement": "ALTERNATIVE",
          "priority": 10,
          "autheticatorFlow": false,
          "userSetupAllowed": false
        },
        {
          "authenticatorFlow": true,
          "requirement": "ALTERNATIVE",
          "priority": 20,
          "autheticatorFlow": true,
          "flowAlias": "Handle Existing Account",
          "userSetupAllowed": false
        }
      ]
    },
    {
      "id": "d7a5ad56-5c40-4878-8f35-e8f1913924e1",
      "alias": "Verify Existing Account by Re-authentication",
      "description": "Reauthentication of existing account",
      "providerId": "basic-flow",
      "topLevel": false,
      "builtIn": true,
      "authenticationExecutions": [
        {
          "authenticator": "idp-username-password-form",
          "authenticatorFlow": false,
          "requirement": "REQUIRED",
          "priority": 10,
          "autheticatorFlow": false,
          "userSetupAllowed": false
        },
        {
          "authenticatorFlow": true,
          "requirement": "CONDITIONAL",
          "priority": 20,
          "autheticatorFlow": true,
          "flowAlias": "First broker login - Conditional 2FA",
          "userSetupAllowed": false
        }
      ]
    },
    {
      "id": "8393960a-9b30-4f1a-8b46-737c2a1b900a",
      "alias": "browser",
      "description": "Browser based authentication",
      "providerId": "basic-flow",
      "topLevel": true,
      "builtIn": true,
      "authenticationExecutions": [
        {
          "authenticator": "auth-cookie",
          "authenticatorFlow": false,
          "requirement": "ALTERNATIVE",
          "priority": 10,
          "autheticatorFlow": false,
          "userSetupAllowed": false
        },
        {
          "authenticator": "auth-spnego",
          "authenticatorFlow": false,
          "requirement": "DISABLED",
          "priority": 20,
          "autheticatorFlow": false,
          "userSetupAllowed": false
        },
        {
          "authenticator": "identity-provider-redirector",
          "authenticatorFlow": false,
          "requirement": "ALTERNATIVE",
          "priority": 25,
          "autheticatorFlow": false,
          "userSetupAllowed": false
        },
        {
          "authenticatorFlow": true,
          "requirement": "ALTERNATIVE",
          "priority": 26,
          "autheticatorFlow": true,
          "flowAlias": "Organization",
          "userSetupAllowed": false
        },
        {
          "authenticatorFlow": true,
          "requirement": "ALTERNATIVE",
          "priority": 30,
          "autheticatorFlow": true,
          "flowAlias": "forms",
          "userSetupAllowed": false
        }
      ]
    },
    {
      "id": "4f35c39f-23bb-4866-8e22-21135c31da8c",
      "alias": "clients",
      "description": "Base authentication for clients",
      "providerId": "client-flow",
      "topLevel": true,
      "builtIn": true,
      "authenticationExecutions": [
        {
          "authenticator": "client-secret",
          "authenticatorFlow": false,
          "requirement": "ALTERNATIVE",
          "priority": 10,
          "autheticatorFlow": false,
          "userSetupAllowed": false
        },
        {
          "authenticator": "client-jwt",
          "authenticatorFlow": false,
          "requirement": "ALTERNATIVE",
          "priority": 20,
          "autheticatorFlow": false,
          "userSetupAllowed": false
        },
        {
          "authenticator": "client-secret-jwt",
          "authenticatorFlow": false,
          "requirement": "ALTERNATIVE",
          "priority": 30,
          "autheticatorFlow": false,
          "userSetupAllowed": false
        },
        {
          "authenticator": "client-x509",
          "authenticatorFlow": false,
          "requirement": "ALTERNATIVE",
          "priority": 40,
          "autheticatorFlow": false,
          "userSetupAllowed": false
        },
        {
          "authenticator": "federated-jwt",
          "authenticatorFlow": false,
          "requirement": "ALTERNATIVE",
          "priority": 50,
          "autheticatorFlow": false,
          "userSetupAllowed": false
        }
      ]
    },
    {
      "id": "d29bd712-b315-4e7e-9277-3b842905b067",
      "alias": "direct grant",
      "description": "OpenID Connect Resource Owner Grant",
      "providerId": "basic-flow",
      "topLevel": true,
      "builtIn": true,
      "authenticationExecutions": [
        {
          "authenticator": "direct-grant-validate-username",
          "authenticatorFlow": false,
          "requirement": "REQUIRED",
          "priority": 10,
          "autheticatorFlow": false,
          "userSetupAllowed": false
        },
        {
          "authenticator": "direct-grant-validate-password",
          "authenticatorFlow": false,
          "requirement": "REQUIRED",
          "priority": 20,
          "autheticatorFlow": false,
          "userSetupAllowed": false
        },
        {
          "authenticatorFlow": true,
          "requirement": "CONDITIONAL",
          "priority": 30,
          "autheticatorFlow": true,
          "flowAlias": "Direct Grant - Conditional OTP",
          "userSetupAllowed": false
        }
      ]
    },
    {
      "id": "aa54b991-cd2b-43ea-9c7d-8e75c24a0194",
      "alias": "docker auth",
      "description": "Used by Docker clients to authenticate against the IDP",
      "providerId": "basic-flow",
      "topLevel": true,
      "builtIn": true,
      "authenticationExecutions": [
        {
          "authenticator": "docker-http-basic-authenticator",
          "authenticatorFlow": false,
          "requirement": "REQUIRED",
          "priority": 10,
          "autheticatorFlow": false,
          "userSetupAllowed": false
        }
      ]
    },
    {
      "id": "05b3b777-4c36-47d9-adec-0e1a6895e5bd",
      "alias": "first broker login",
      "description": "Actions taken after first broker login with identity provider account, which is not yet linked to any Keycloak account",
      "providerId": "basic-flow",
      "topLevel": true,
      "builtIn": true,
      "authenticationExecutions": [
        {
          "authenticatorConfig": "review profile config",
          "authenticator": "idp-review-profile",
          "authenticatorFlow": false,
          "requirement": "REQUIRED",
          "priority": 10,
          "autheticatorFlow": false,
          "userSetupAllowed": false
        },
        {
          "authenticatorFlow": true,
          "requirement": "REQUIRED",
          "priority": 20,
          "autheticatorFlow": true,
          "flowAlias": "User creation or linking",
          "userSetupAllowed": false
        },
        {
          "authenticatorFlow": true,
          "requirement": "CONDITIONAL",
          "priority": 60,
          "autheticatorFlow": true,
          "flowAlias": "First Broker Login - Conditional Organization",
          "userSetupAllowed": false
        }
      ]
    },
    {
      "id": "0c1d5c09-f200-4e62-97f8-1342fa3d6ed4",
      "alias": "forms",
      "description": "Username, password, otp and other auth forms.",
      "providerId": "basic-flow",
      "topLevel": false,
      "builtIn": true,
      "authenticationExecutions": [
        {
          "authenticator": "auth-username-password-form",
          "authenticatorFlow": false,
          "requirement": "REQUIRED",
          "priority": 10,
          "autheticatorFlow": false,
          "userSetupAllowed": false
        },
        {
          "authenticatorFlow": true,
          "requirement": "CONDITIONAL",
          "priority": 20,
          "autheticatorFlow": true,
          "flowAlias": "Browser - Conditional 2FA",
          "userSetupAllowed": false
        }
      ]
    },
    {
      "id": "0006b8bb-980a-4b97-830f-c3b701f9fbea",
      "alias": "registration",
      "description": "Registration flow",
      "providerId": "basic-flow",
      "topLevel": true,
      "builtIn": true,
      "authenticationExecutions": [
        {
          "authenticator": "registration-page-form",
          "authenticatorFlow": true,
          "requirement": "REQUIRED",
          "priority": 10,
          "autheticatorFlow": true,
          "flowAlias": "registration form",
          "userSetupAllowed": false
        }
      ]
    },
    {
      "id": "784dc6fd-74c8-40b1-a58c-7a6752b3bd9c",
      "alias": "registration form",
      "description": "Registration form",
      "providerId": "form-flow",
      "topLevel": false,
      "builtIn": true,
      "authenticationExecutions": [
        {
          "authenticator": "registration-user-creation",
          "authenticatorFlow": false,
          "requirement": "REQUIRED",
          "priority": 20,
          "autheticatorFlow": false,
          "userSetupAllowed": false
        },
        {
          "authenticator": "registration-password-action",
          "authenticatorFlow": false,
          "requirement": "REQUIRED",
          "priority": 50,
          "autheticatorFlow": false,
          "userSetupAllowed": false
        },
        {
          "authenticator": "registration-recaptcha-action",
          "authenticatorFlow": false,
          "requirement": "DISABLED",
          "priority": 60,
          "autheticatorFlow": false,
          "userSetupAllowed": false
        },
        {
          "authenticator": "registration-terms-and-conditions",
          "authenticatorFlow": false,
          "requirement": "DISABLED",
          "priority": 70,
          "autheticatorFlow": false,
          "userSetupAllowed": false
        }
      ]
    },
    {
      "id": "590bc721-f88e-4b60-baf1-e0d08ce4a04e",
      "alias": "reset credentials",
      "description": "Reset credentials for a user if they forgot their password or something",
      "providerId": "basic-flow",
      "topLevel": true,
      "builtIn": true,
      "authenticationExecutions": [
        {
          "authenticator": "reset-credentials-choose-user",
          "authenticatorFlow": false,
          "requirement": "REQUIRED",
          "priority": 10,
          "autheticatorFlow": false,
          "userSetupAllowed": false
        },
        {
          "authenticator": "reset-credential-email",
          "authenticatorFlow": false,
          "requirement": "REQUIRED",
          "priority": 20,
          "autheticatorFlow": false,
          "userSetupAllowed": false
        },
        {
          "authenticator": "reset-password",
          "authenticatorFlow": false,
          "requirement": "REQUIRED",
          "priority": 30,
          "autheticatorFlow": false,
          "userSetupAllowed": false
        },
        {
          "authenticatorFlow": true,
          "requirement": "CONDITIONAL",
          "priority": 40,
          "autheticatorFlow": true,
          "flowAlias": "Reset - Conditional OTP",
          "userSetupAllowed": false
        }
      ]
    },
    {
      "id": "e1c5c6a2-9aee-49ce-97b3-a84fd708b326",
      "alias": "saml ecp",
      "description": "SAML ECP Profile Authentication Flow",
      "providerId": "basic-flow",
      "topLevel": true,
      "builtIn": true,
      "authenticationExecutions": [
        {
          "authenticator": "http-basic-authenticator",
          "authenticatorFlow": false,
          "requirement": "REQUIRED",
          "priority": 10,
          "autheticatorFlow": false,
          "userSetupAllowed": false
        }
      ]
    }
  ],
  "authenticatorConfig": [
    {
      "id": "7d0dc97d-f575-4ca3-8347-0c62c54f1170",
      "alias": "browser-conditional-credential",
      "config": {
        "credentials": "webauthn-passwordless"
      }
    },
    {
      "id": "4d60e273-ca1b-4c83-acca-15c528af557f",
      "alias": "create unique user config",
      "config": {
        "require.password.update.after.registration": "false"
      }
    },
    {
      "id": "081a8676-dbee-4e6d-bebf-a68b84adbdb0",
      "alias": "first-broker-login-conditional-credential",
      "config": {
        "credentials": "webauthn-passwordless"
      }
    },
    {
      "id": "72e13ee9-4aa9-410c-bcb8-c3a075adf80b",
      "alias": "review profile config",
      "config": {
        "update.profile.on.first.login": "missing"
      }
    }
  ],
  "requiredActions": [
    {
      "alias": "CONFIGURE_TOTP",
      "name": "Configure OTP",
      "providerId": "CONFIGURE_TOTP",
      "enabled": true,
      "defaultAction": false,
      "priority": 10,
      "config": {}
    },
    {
      "alias": "TERMS_AND_CONDITIONS",
      "name": "Terms and Conditions",
      "providerId": "TERMS_AND_CONDITIONS",
      "enabled": false,
      "defaultAction": false,
      "priority": 20,
      "config": {}
    },
    {
      "alias": "UPDATE_PASSWORD",
      "name": "Update Password",
      "providerId": "UPDATE_PASSWORD",
      "enabled": true,
      "defaultAction": false,
      "priority": 30,
      "config": {}
    },
    {
      "alias": "UPDATE_PROFILE",
      "name": "Update Profile",
      "providerId": "UPDATE_PROFILE",
      "enabled": true,
      "defaultAction": false,
      "priority": 40,
      "config": {}
    },
    {
      "alias": "VERIFY_EMAIL",
      "name": "Verify Email",
      "providerId": "VERIFY_EMAIL",
      "enabled": true,
      "defaultAction": false,
      "priority": 50,
      "config": {}
    },
    {
      "alias": "delete_account",
      "name": "Delete Account",
      "providerId": "delete_account",
      "enabled": false,
      "defaultAction": false,
      "priority": 60,
      "config": {}
    },
    {
      "alias": "UPDATE_EMAIL",
      "name": "Update Email",
      "providerId": "UPDATE_EMAIL",
      "enabled": false,
      "defaultAction": false,
      "priority": 70,
      "config": {}
    },
    {
      "alias": "webauthn-register",
      "name": "Webauthn Register",
      "providerId": "webauthn-register",
      "enabled": true,
      "defaultAction": false,
      "priority": 80,
      "config": {}
    },
    {
      "alias": "webauthn-register-passwordless",
      "name": "Webauthn Register Passwordless",
      "providerId": "webauthn-register-passwordless",
      "enabled": true,
      "defaultAction": false,
      "priority": 90,
      "config": {}
    },
    {
      "alias": "VERIFY_PROFILE",
      "name": "Verify Profile",
      "providerId": "VERIFY_PROFILE",
      "enabled": true,
      "defaultAction": false,
      "priority": 100,
      "config": {}
    },
    {
      "alias": "delete_credential",
      "name": "Delete Credential",
      "providerId": "delete_credential",
      "enabled": true,
      "defaultAction": false,
      "priority": 110,
      "config": {}
    },
    {
      "alias": "idp_link",
      "name": "Linking Identity Provider",
      "providerId": "idp_link",
      "enabled": true,
      "defaultAction": false,
      "priority": 120,
      "config": {}
    },
    {
      "alias": "CONFIGURE_RECOVERY_AUTHN_CODES",
      "name": "Recovery Authentication Codes",
      "providerId": "CONFIGURE_RECOVERY_AUTHN_CODES",
      "enabled": true,
      "defaultAction": false,
      "priority": 130,
      "config": {}
    },
    {
      "alias": "update_user_locale",
      "name": "Update User Locale",
      "providerId": "update_user_locale",
      "enabled": true,
      "defaultAction": false,
      "priority": 1000,
      "config": {}
    }
  ],
  "browserFlow": "browser",
  "registrationFlow": "registration",
  "directGrantFlow": "direct grant",
  "resetCredentialsFlow": "reset credentials",
  "clientAuthenticationFlow": "clients",
  "dockerAuthenticationFlow": "docker auth",
  "firstBrokerLoginFlow": "first broker login",
  "attributes": {
    "cibaBackchannelTokenDeliveryMode": "poll",
    "cibaExpiresIn": "120",
    "cibaAuthRequestedUserHint": "login_hint",
    "oauth2DeviceCodeLifespan": "600",
    "oauth2DevicePollingInterval": "5",
    "parRequestUriLifespan": "60",
    "cibaInterval": "5",
    "realmReusableOtpCode": "false"
  },
  "keycloakVersion": "26.6.0",
  "userManagedAccessAllowed": false,
  "organizationsEnabled": false,
  "verifiableCredentialsEnabled": false,
  "adminPermissionsEnabled": false,
  "scimApiEnabled": false,
  "clientProfiles": {
    "profiles": []
  },
  "clientPolicies": {
    "policies": []
  }
}